virtualenv/__init__.py
virtualenv/__main__.py
virtualenv/info.py
virtualenv/report.py
virtualenv/version.py
virtualenv/activation/__init__.py
virtualenv/activation/activator.py
virtualenv/activation/via_template.py
virtualenv/activation/bash/__init__.py
virtualenv/activation/bash/activate.sh
virtualenv/activation/batch/__init__.py
virtualenv/activation/batch/activate.bat
virtualenv/activation/batch/deactivate.bat
virtualenv/activation/batch/pydoc.bat
virtualenv/activation/cshell/__init__.py
virtualenv/activation/cshell/activate.csh
virtualenv/activation/fish/__init__.py
virtualenv/activation/fish/activate.fish
virtualenv/activation/nushell/__init__.py
virtualenv/activation/nushell/activate.nu
virtualenv/activation/powershell/__init__.py
virtualenv/activation/powershell/activate.ps1
virtualenv/activation/python/__init__.py
virtualenv/activation/python/activate_this.py
virtualenv/app_data/__init__.py
virtualenv/app_data/base.py
virtualenv/app_data/na.py
virtualenv/app_data/read_only.py
virtualenv/app_data/via_disk_folder.py
virtualenv/app_data/via_tempdir.py
virtualenv/config/__init__.py
virtualenv/config/convert.py
virtualenv/config/env_var.py
virtualenv/config/ini.py
virtualenv/config/cli/__init__.py
virtualenv/config/cli/parser.py
virtualenv/create/__init__.py
virtualenv/create/creator.py
virtualenv/create/debug.py
virtualenv/create/describe.py
virtualenv/create/pyenv_cfg.py
virtualenv/create/via_global_ref/__init__.py
virtualenv/create/via_global_ref/_virtualenv.py
virtualenv/create/via_global_ref/api.py
virtualenv/create/via_global_ref/store.py
virtualenv/create/via_global_ref/venv.py
virtualenv/create/via_global_ref/builtin/__init__.py
virtualenv/create/via_global_ref/builtin/builtin_way.py
virtualenv/create/via_global_ref/builtin/ref.py
virtualenv/create/via_global_ref/builtin/via_global_self_do.py
virtualenv/create/via_global_ref/builtin/cpython/__init__.py
virtualenv/create/via_global_ref/builtin/cpython/common.py
virtualenv-20.35.2.dist-info/METADATA
virtualenv-20.35.2.dist-info/WHEEL
virtualenv-20.35.2.dist-info/entry_points.txt
virtualenv-20.35.2.dist-info/licenses/LICENSE
virtualenv-20.35.2.dist-info/RECORD
